[
  { "id": "drum_rock_001", "instrument": "drums", "meter": "4/4", "density": "med", "length_bars": 2, "midi_file": "drums/rock_001.mid", "tags": ["groove"] },
  { "id": "drum_fill_01",  "instrument": "drums", "meter": "4/4", "density": "busy","length_bars": 1, "midi_file": "drums/rock_fill_01.mid", "tags": ["fill"] },

  { "id": "bass_root5_001","instrument": "bass",  "meter": "4/4", "density": "sparse","length_bars": 2, "midi_file": "bass/root5_001.mid" },
  { "id": "bass_walk_001", "instrument": "bass",  "meter": "4/4", "density": "med",   "length_bars": 2, "midi_file": "bass/walking_001.mid" },

  { "id": "keys_comp_001", "instrument": "keys",  "meter": "4/4", "density": "sparse","length_bars": 2, "midi_file": "keys/comping_grid_001.mid" },

  { "id": "pad_sus_001",   "instrument": "pads",  "meter": "4/4", "density": "sparse","length_bars": 4, "midi_file": "pads/pad_sustain_001.mid" }
]
